mp3_to_wav/__init__.py
mp3_to_wav/converter.py
zz_mp3_to_wav-1.0.2.dist-info/METADATA
zz_mp3_to_wav-1.0.2.dist-info/WHEEL
zz_mp3_to_wav-1.0.2.dist-info/top_level.txt
zz_mp3_to_wav-1.0.2.dist-info/RECORD
