Metadata-Version: 2.4
Name: zz-mp3-to-wav
Version: 1.0.2
Summary: 基于ffmpeg的MP3转WAV工具
Author: zhangzeng
Classifier: Programming Language :: Python :: 3
Classifier: License :: OSI Approved :: MIT License
Classifier: Operating System :: OS Independent
Requires-Python: >=3.8
